{
  "3bd6dc29-4b89-4cf3-a15d-c95e520a5808": {
    "save": {
      "level": 334,
      "exp": 732537,
      "gold": 9566434,
      "unlockedNodes": [
        "center",
        "minotaur_category",
        "doubleStrike",
        "sharpshooter",
        "openingStrike",
        "powerBolt",
        "burstArrow",
        "tripleStrike",
        "followUp",
        "headshot",
        "strongerBullets",
        "ricochet",
        "unlockFireball",
        "unlockHeavyMagic",
        "unlockLightMagic",
        "lightMagicCooldown",
        "lightMagicDamage",
        "fireballDamage",
        "fireballCooldown",
        "heavyMagicDamage",
        "heavyMagicCooldown",
        "experiencedHunter",
        "deepPockets",
        "gearingUp",
        "uberDifficulty",
        "materialistic",
        "likeABoss",
        "lootHungry",
        "focusedBarrage",
        "bleedingCritical"
      ],
      "monsterResearch": {
        "Cave Rat": {
          "kills": 34485,
          "unlocked": [
            0,
            1,
            2
          ]
        },
        "Rat": {
          "kills": 86252,
          "unlocked": [
            0,
            1,
            2,
            3
          ]
        },
        "Poison Spider": {
          "kills": 83484,
          "unlocked": [
            0,
            1,
            2,
            3
          ]
        },
        "Tarantula": {
          "kills": 38004,
          "unlocked": [
            0,
            1,
            2
          ]
        },
        "Carrion Worm": {
          "kills": 745,
          "unlocked": []
        },
        "Cyclops": {
          "kills": 13306,
          "unlocked": [
            0,
            1,
            2
          ]
        },
        "Cyclops Drone": {
          "kills": 5412,
          "unlocked": [
            0,
            1
          ]
        },
        "Cyclops Smith": {
          "kills": 1979,
          "unlocked": [
            0
          ]
        },
        "Dark Monk": {
          "kills": 19025,
          "unlocked": [
            0,
            1,
            2
          ]
        },
        "Witch": {
          "kills": 3954,
          "unlocked": [
            0
          ]
        },
        "Assassin": {
          "kills": 6628,
          "unlocked": [
            0,
            1
          ]
        },
        "Bonebeast": {
          "kills": 13190,
          "unlocked": [
            0,
            1,
            2
          ]
        },
        "Ancient Scarab": {
          "kills": 65660,
          "unlocked": [
            0,
            1,
            2,
            3
          ]
        },
        "Scarab": {
          "kills": 33088,
          "unlocked": [
            0,
            1,
            2
          ]
        },
        "Gargoyle": {
          "kills": 16097,
          "unlocked": [
            0,
            1,
            2
          ]
        },
        "Stone Golem": {
          "kills": 7199,
          "unlocked": [
            0,
            1
          ]
        },
        "Thornback Tortoise": {
          "kills": 4054,
          "unlocked": [
            0
          ]
        },
        "Kongra": {
          "kills": 4724,
          "unlocked": [
            0
          ]
        },
        "Sibang": {
          "kills": 13780,
          "unlocked": [
            0,
            1,
            2
          ]
        },
        "Merlkin": {
          "kills": 8116,
          "unlocked": [
            0,
            1
          ]
        },
        "Vampire": {
          "kills": 29595,
          "unlocked": [
            0,
            1,
            2
          ]
        },
        "Vampire Bride": {
          "kills": 10422,
          "unlocked": [
            0,
            1,
            2
          ]
        },
        "Necromancer": {
          "kills": 7304,
          "unlocked": [
            0,
            1
          ]
        },
        "Hero": {
          "kills": 22427,
          "unlocked": [
            0,
            1,
            2
          ]
        },
        "Vile Grandmaster": {
          "kills": 7619,
          "unlocked": [
            0,
            1
          ]
        },
        "Monk": {
          "kills": 6834,
          "unlocked": [
            0,
            1
          ]
        },
        "Lizard Dragon Priest": {
          "kills": 21238,
          "unlocked": [
            0,
            1,
            2
          ]
        },
        "Lizard High Guard": {
          "kills": 16729,
          "unlocked": [
            0,
            1,
            2
          ]
        },
        "Lizard Chosen": {
          "kills": 47124,
          "unlocked": [
            0,
            1,
            2
          ]
        },
        "Rotworm": {
          "kills": 2358,
          "unlocked": [
            0
          ]
        },
        "Frost Dragon Hatchling": {
          "kills": 908,
          "unlocked": []
        },
        "Frost Dragon": {
          "kills": 2012,
          "unlocked": [
            0
          ]
        },
        "Crystal Spider": {
          "kills": 598,
          "unlocked": []
        }
      },
      "weaponStarLevel": 0,
      "dracoWeaponScaling": 0,
      "starsEarned": 0,
      "stars": 19326,
      "observatory": {
        "active": false,
        "closesAt": 0,
        "nextCheckAt": 1778341071921
      },
      "starSystem": {
        "activeZoneId": 15,
        "nextZoneSwapAt": 1778341791898,
        "nextSpawnCheckAt": 1778341017899
      },
      "starUpgrades": {
        "starfall": 30,
        "starShower": 14,
        "astralShower": 2,
        "supernovas": 0,
        "supergiants": 0,
        "novaYields": 0,
        "giantYields": 0,
        "cosmicWorth": 0,
        "starHole": 0,
        "stellarYield": 0
      },
      "constellations": {
        "gemini": 0,
        "aries": 0,
        "sagittarius": 0,
        "aquarius": 0,
        "phoenix": 0,
        "draco": 0,
        "taurus": 0,
        "cancer": 0,
        "orion": 0,
        "cetus": 0
      },
      "settings": {
        "minotaurAttacks": true,
        "necromancerAttacks": true,
        "minotaurEffectDebug": false,
        "followStars": false,
        "autoCollectStars": false
      },
      "dpsSamples": {
        "minotaur": [
          {
            "time": 1778332644843,
            "value": 5120
          }
        ],
        "necromancer": [
          {
            "time": 1778332644843,
            "value": 1194
          }
        ]
      },
      "filters": {
        "equipmentAction": "none",
        "rarityLimit": "common"
      },
      "skeletons": [],
      "rebirth": {
        "count": 1,
        "coins": 0
      },
      "rebirthUpgrades": {
        "autoSkills": 1,
        "keepMaterials": 1
      },
      "equipment": {
        "necklace": {
          "id": "67599a62-3dcb-4909-9bef-cb7e1db138db",
          "type": "necklace",
          "tier": 3,
          "rarity": "legendary",
          "rarityName": "Legendary",
          "rarityColor": "#ffb84d",
          "name": "Elven Amulet",
          "icon": "📿",
          "sprite": "assets/equipment/necklace/elven_amulet.gif",
          "stats": {
            "crit": 1,
            "attackSpeed": 17,
            "whetstoneChance": 21,
            "damage": 14
          },
          "enhanceLevel": 0
        },
        "helmet": {
          "id": "c5c6928b-2a3d-4e19-9fac-9af7c095686d",
          "type": "helmet",
          "tier": 3,
          "rarity": "rare",
          "rarityName": "Rare",
          "rarityColor": "#4dabf7",
          "name": "Chain Helmet",
          "icon": "⛑",
          "sprite": "assets/equipment/helmet/chain_helmet.gif",
          "stats": {
            "critDamage": 63,
            "gold": 4,
            "crit": 5
          },
          "enhanceLevel": 6
        },
        "armor": {
          "id": "b83b96b8-c384-474a-ad70-c2cde1c9773d",
          "type": "armor",
          "tier": 4,
          "rarity": "rare",
          "rarityName": "Rare",
          "rarityColor": "#4dabf7",
          "name": "Chain Armor",
          "icon": "🥋",
          "sprite": "assets/equipment/armor/chain_armor.gif",
          "stats": {
            "gold": 5,
            "exp": 5,
            "whetstoneChance": 11
          },
          "enhanceLevel": 3
        },
        "shield": {
          "id": "b2fefbca-1b59-4192-ac3b-a1f186bfbaa8",
          "type": "shield",
          "tier": 3,
          "rarity": "rare",
          "rarityName": "Rare",
          "rarityColor": "#4dabf7",
          "name": "Brass Shield",
          "icon": "🛡",
          "sprite": "assets/equipment/shield/brass_shield.gif",
          "stats": {
            "crit": 5,
            "researchEcho": 9,
            "critDamage": 54
          },
          "enhanceLevel": 6
        },
        "ring": {
          "id": "42e28b04-288b-4a10-9f8a-a6db8deaf9ac",
          "type": "ring",
          "tier": 2,
          "rarity": "legendary",
          "rarityName": "Legendary",
          "rarityColor": "#ffb84d",
          "name": "Butterfly Ring",
          "icon": "💍",
          "sprite": "assets/equipment/ring/butterfly_ring.gif",
          "stats": {
            "damage": 9,
            "lootChance": 24,
            "attackSpeed": 12,
            "gold": 4
          },
          "enhanceLevel": 3
        },
        "legs": {
          "id": "ee14d899-138e-4fca-b0c2-b71823d1f609",
          "type": "legs",
          "tier": 4,
          "rarity": "legendary",
          "rarityName": "Legendary",
          "rarityColor": "#ffb84d",
          "name": "Brass Legs",
          "icon": "👖",
          "sprite": "assets/equipment/legs/brass_legs.gif",
          "stats": {
            "damage": 9,
            "crit": 2,
            "whetstoneChance": 27,
            "doubleDrop": 9
          },
          "enhanceLevel": 4
        },
        "shoes": {
          "id": "04c62ca8-3fbe-4cc3-8eb7-6a8b62e03408",
          "type": "shoes",
          "tier": 3,
          "rarity": "legendary",
          "rarityName": "Legendary",
          "rarityColor": "#ffb84d",
          "name": "Sandals",
          "icon": "🥾",
          "sprite": "assets/equipment/shoes/sandals.gif",
          "stats": {
            "attackSpeed": 3,
            "damage": 7,
            "exp": 7,
            "researchEcho": 21
          },
          "enhanceLevel": 4
        }
      },
      "equipmentInventory": [],
      "salvageMaterials": {
        "commonMaterial": 1950,
        "uncommonMaterial": 1400,
        "rareMaterial": 471,
        "legendaryMaterial": 186
      },
      "depot": {
        "activeTab": 0,
        "tabs": [
          [
            null,
            null,
            null,
            null,
            null,
            null,
            null,
            null,
            null,
            null,
            null,
            null,
            null,
            null,
            null,
            null,
            null,
            null,
            null,
            null,
            null,
            null,
            null,
            null,
            null,
            null,
            null,
            null,
            null,
            null,
            null,
            null,
            null,
            null,
            null,
            null,
            null,
            null,
            null,
            null
          ],
          [
            null,
            null,
            null,
            null,
            null,
            null,
            null,
            null,
            null,
            null,
            null,
            null,
            null,
            null,
            null,
            null,
            null,
            null,
            null,
            null,
            null,
            null,
            null,
            null,
            null,
            null,
            null,
            null,
            null,
            null,
            null,
            null,
            null,
            null,
            null,
            null,
            null,
            null,
            null,
            null
          ],
          [
            null,
            null,
            null,
            null,
            null,
            null,
            null,
            null,
            null,
            null,
            null,
            null,
            null,
            null,
            null,
            null,
            null,
            null,
            null,
            null,
            null,
            null,
            null,
            null,
            null,
            null,
            null,
            null,
            null,
            null,
            null,
            null,
            null,
            null,
            null,
            null,
            null,
            null,
            null,
            null
          ]
        ]
      },
      "activeLogFilter": "all",
      "logMessages": [
        {
          "text": "🪙 Frost Dragon Hatchling killed. +2.5K gold, +2.6K exp.",
          "type": "combat",
          "time": 1778341014556
        },
        {
          "text": "🪙 Frost Dragon killed. +2.2K gold, +3.6K exp.",
          "type": "combat",
          "time": 1778341013956
        },
        {
          "text": "🪙 Frost Dragon killed. +2.6K gold, +3.5K exp.",
          "type": "combat",
          "time": 1778341013648
        },
        {
          "text": "💀 Minotaur Archer crit for 22K!",
          "type": "system",
          "time": 1778341012430
        },
        {
          "text": "🪙 Frost Dragon killed. +2.2K gold, +2.9K exp.",
          "type": "combat",
          "time": 1778341012429
        },
        {
          "text": "🪙 Frost Dragon Hatchling killed. +2.8K gold, +3.1K exp.",
          "type": "combat",
          "time": 1778341012423
        },
        {
          "text": "🪙 Frost Dragon Hatchling killed. +2.1K gold, +3.0K exp.",
          "type": "combat",
          "time": 1778341011857
        },
        {
          "text": "🪙 Frost Dragon Hatchling killed. +2.1K gold, +3.2K exp.",
          "type": "combat",
          "time": 1778341011603
        },
        {
          "text": "🪙 Frost Dragon Hatchling killed. +2.1K gold, +3.2K exp.",
          "type": "combat",
          "time": 1778341011595
        },
        {
          "text": "🪙 Frost Dragon Hatchling killed. +2.2K gold, +2.7K exp.",
          "type": "combat",
          "time": 1778341011120
        },
        {
          "text": "🪙 Crystal Spider killed. +2.7K gold, +3.7K exp.",
          "type": "combat",
          "time": 1778341011117
        },
        {
          "text": "🪙 Frost Dragon Hatchling killed. +2.4K gold, +3.2K exp.",
          "type": "combat",
          "time": 1778340951906
        },
        {
          "text": "🪙 Frost Dragon Hatchling killed. +2.6K gold, +3.3K exp.",
          "type": "combat",
          "time": 1778340951905
        },
        {
          "text": "🪙 Frost Dragon killed. +2.6K gold, +2.7K exp.",
          "type": "combat",
          "time": 1778340891905
        },
        {
          "text": "✨ Stars are now falling in Medusa Tower!",
          "type": "system",
          "time": 1778340891899
        },
        {
          "text": "🪙 Crystal Spider killed. +2.4K gold, +2.9K exp.",
          "type": "combat",
          "time": 1778340831895
        },
        {
          "text": "🪙 Frost Dragon Hatchling killed. +2.4K gold, +3.0K exp.",
          "type": "combat",
          "time": 1778340831893
        },
        {
          "text": "🪙 Crystal Spider killed. +2.0K gold, +3.8K exp.",
          "type": "combat",
          "time": 1778340831891
        },
        {
          "text": "🪙 Frost Dragon killed. +1.9K gold, +2.8K exp.",
          "type": "combat",
          "time": 1778340771906
        },
        {
          "text": "🪙 Frost Dragon killed. +1.9K gold, +3.3K exp.",
          "type": "combat",
          "time": 1778340711918
        },
        {
          "text": "⚪ You received 1 Silver Token.",
          "type": "system",
          "time": 1778340711916
        },
        {
          "text": "🪙 Frost Dragon Hatchling killed. +2.1K gold, +2.7K exp.",
          "type": "combat",
          "time": 1778340711915
        },
        {
          "text": "🪙 Frost Dragon Hatchling killed. +2.8K gold, +2.9K exp.",
          "type": "combat",
          "time": 1778340651898
        },
        {
          "text": "🪙 Frost Dragon killed. +2.8K gold, +2.8K exp.",
          "type": "combat",
          "time": 1778340573895
        },
        {
          "text": "🪙 Frost Dragon killed. +2.5K gold, +2.7K exp.",
          "type": "combat",
          "time": 1778340573893
        },
        {
          "text": "🪙 Frost Dragon killed. +2.5K gold, +3.6K exp.",
          "type": "combat",
          "time": 1778340565893
        },
        {
          "text": "🪙 Frost Dragon killed. +2.5K gold, +2.6K exp.",
          "type": "combat",
          "time": 1778340562901
        },
        {
          "text": "🪙 Crystal Spider killed. +2.3K gold, +3.5K exp.",
          "type": "combat",
          "time": 1778340552896
        },
        {
          "text": "🪙 Frost Dragon Hatchling killed. +2.0K gold, +2.6K exp.",
          "type": "combat",
          "time": 1778340532890
        },
        {
          "text": "🪙 Frost Dragon killed. +2.5K gold, +3.4K exp.",
          "type": "combat",
          "time": 1778340516490
        },
        {
          "text": "💀 Minotaur Archer crit for 38K!",
          "type": "system",
          "time": 1778340515957
        },
        {
          "text": "🪙 Crystal Spider killed. +2.5K gold, +2.9K exp.",
          "type": "combat",
          "time": 1778340515956
        },
        {
          "text": "🪙 Frost Dragon killed. +2.8K gold, +3.4K exp.",
          "type": "combat",
          "time": 1778340515649
        },
        {
          "text": "💀 Minotaur Archer crit for 38K!",
          "type": "system",
          "time": 1778340515336
        },
        {
          "text": "🪙 Crystal Spider killed. +2.6K gold, +3.5K exp.",
          "type": "combat",
          "time": 1778340515336
        },
        {
          "text": "🪙 Frost Dragon Hatchling killed. +2.0K gold, +3.2K exp.",
          "type": "combat",
          "time": 1778340515032
        },
        {
          "text": "🪙 Frost Dragon killed. +2.5K gold, +2.5K exp.",
          "type": "combat",
          "time": 1778340514694
        },
        {
          "text": "🪙 Frost Dragon Hatchling killed. +1.9K gold, +3.3K exp.",
          "type": "combat",
          "time": 1778340514122
        },
        {
          "text": "🪙 Frost Dragon Hatchling killed. +2.5K gold, +3.4K exp.",
          "type": "combat",
          "time": 1778340513811
        },
        {
          "text": "🪙 Frost Dragon killed. +1.9K gold, +2.8K exp.",
          "type": "combat",
          "time": 1778340513498
        },
        {
          "text": "🪙 Frost Dragon killed. +2.1K gold, +3.5K exp.",
          "type": "combat",
          "time": 1778340513280
        },
        {
          "text": "🪙 Crystal Spider killed. +2.1K gold, +3.2K exp.",
          "type": "combat",
          "time": 1778340512874
        },
        {
          "text": "💀 Minotaur Archer crit for 27K!",
          "type": "system",
          "time": 1778340512053
        },
        {
          "text": "🪙 Frost Dragon killed. +2.5K gold, +2.9K exp.",
          "type": "combat",
          "time": 1778340512052
        },
        {
          "text": "💀 Minotaur Archer crit for 20K!",
          "type": "system",
          "time": 1778340512026
        },
        {
          "text": "🪙 Frost Dragon killed. +2.3K gold, +2.5K exp.",
          "type": "combat",
          "time": 1778340512025
        },
        {
          "text": "💀 Minotaur Archer crit for 26K!",
          "type": "system",
          "time": 1778340511194
        },
        {
          "text": "🪙 Frost Dragon Hatchling killed. +2.4K gold, +3.3K exp.",
          "type": "combat",
          "time": 1778340511194
        },
        {
          "text": "🪙 Frost Dragon killed. +1.9K gold, +3.7K exp.",
          "type": "combat",
          "time": 1778340511193
        },
        {
          "text": "💀 Minotaur Archer crit for 34K!",
          "type": "system",
          "time": 1778340510878
        },
        {
          "text": "🪙 Frost Dragon killed. +2.8K gold, +2.8K exp.",
          "type": "combat",
          "time": 1778340510877
        },
        {
          "text": "💀 Minotaur Archer crit for 32K!",
          "type": "system",
          "time": 1778340510603
        },
        {
          "text": "🪙 Frost Dragon Hatchling killed. +2.9K gold, +2.8K exp.",
          "type": "combat",
          "time": 1778340510602
        },
        {
          "text": "💀 Minotaur Archer crit for 20K!",
          "type": "system",
          "time": 1778340510293
        },
        {
          "text": "🪙 Frost Dragon killed. +2.8K gold, +3.7K exp.",
          "type": "combat",
          "time": 1778340510292
        },
        {
          "text": "🪙 Frost Dragon killed. +2.8K gold, +2.5K exp.",
          "type": "combat",
          "time": 1778340510292
        },
        {
          "text": "🪙 Frost Dragon Hatchling killed. +2.9K gold, +3.1K exp.",
          "type": "combat",
          "time": 1778340509993
        },
        {
          "text": "💀 Minotaur Archer crit for 30K!",
          "type": "system",
          "time": 1778340509677
        },
        {
          "text": "🪙 Frost Dragon killed. +2.4K gold, +3.4K exp.",
          "type": "combat",
          "time": 1778340509677
        },
        {
          "text": "💀 Minotaur Archer crit for 26K!",
          "type": "system",
          "time": 1778340509364
        },
        {
          "text": "🪙 Crystal Spider killed. +2.1K gold, +3.8K exp.",
          "type": "combat",
          "time": 1778340509363
        },
        {
          "text": "💀 Minotaur Archer crit for 23K!",
          "type": "system",
          "time": 1778340508488
        },
        {
          "text": "🪙 Frost Dragon killed. +1.8K gold, +3.5K exp.",
          "type": "combat",
          "time": 1778340508487
        },
        {
          "text": "🪙 Frost Dragon killed. +2.4K gold, +2.7K exp.",
          "type": "combat",
          "time": 1778340508486
        },
        {
          "text": "💀 Minotaur Archer crit for 38K!",
          "type": "system",
          "time": 1778340508177
        },
        {
          "text": "🪙 Frost Dragon killed. +2.1K gold, +2.6K exp.",
          "type": "combat",
          "time": 1778340508176
        },
        {
          "text": "💀 Minotaur Archer crit for 24K!",
          "type": "system",
          "time": 1778340507824
        },
        {
          "text": "🪙 Frost Dragon killed. +2.9K gold, +3.6K exp.",
          "type": "combat",
          "time": 1778340507823
        },
        {
          "text": "🪙 Frost Dragon Hatchling killed. +2.8K gold, +2.7K exp.",
          "type": "combat",
          "time": 1778340507822
        },
        {
          "text": "💀 Minotaur Archer crit for 35K!",
          "type": "system",
          "time": 1778340507245
        },
        {
          "text": "🪙 Frost Dragon killed. +2.5K gold, +3.6K exp.",
          "type": "combat",
          "time": 1778340507244
        },
        {
          "text": "🪙 Frost Dragon killed. +2.7K gold, +3.7K exp.",
          "type": "combat",
          "time": 1778340506918
        },
        {
          "text": "💀 Minotaur Archer crit for 22K!",
          "type": "system",
          "time": 1778340506897
        },
        {
          "text": "🪙 Frost Dragon Hatchling killed. +2.7K gold, +3.1K exp.",
          "type": "combat",
          "time": 1778340506896
        },
        {
          "text": "💀 Minotaur Archer crit for 23K!",
          "type": "system",
          "time": 1778340506377
        },
        {
          "text": "🪙 Crystal Spider killed. +1.8K gold, +2.5K exp.",
          "type": "combat",
          "time": 1778340506376
        },
        {
          "text": "💀 Minotaur Archer crit for 26K!",
          "type": "system",
          "time": 1778340505741
        },
        {
          "text": "🪙 Frost Dragon killed. +2.9K gold, +3.2K exp.",
          "type": "combat",
          "time": 1778340505739
        },
        {
          "text": "🪙 Crystal Spider killed. +2.5K gold, +3.5K exp.",
          "type": "combat",
          "time": 1778340505725
        },
        {
          "text": "🪙 Frost Dragon killed. +1.8K gold, +3.2K exp.",
          "type": "combat",
          "time": 1778340504805
        },
        {
          "text": "🪙 Frost Dragon killed. +2.9K gold, +3.4K exp.",
          "type": "combat",
          "time": 1778340504591
        },
        {
          "text": "💀 Minotaur Archer crit for 29K!",
          "type": "system",
          "time": 1778340503932
        },
        {
          "text": "🪙 Frost Dragon killed. +2.0K gold, +3.2K exp.",
          "type": "combat",
          "time": 1778340503931
        },
        {
          "text": "🧩 Rare Chain Armor dropped!",
          "type": "loot",
          "time": 1778340503637
        },
        {
          "text": "🪙 Frost Dragon Hatchling killed. +2.9K gold, +3.2K exp.",
          "type": "combat",
          "time": 1778340503636
        },
        {
          "text": "🪙 Frost Dragon killed. +2.3K gold, +3.2K exp.",
          "type": "combat",
          "time": 1778340503381
        },
        {
          "text": "🪙 Crystal Spider killed. +2.3K gold, +3.3K exp.",
          "type": "combat",
          "time": 1778340503060
        },
        {
          "text": "💀 Minotaur Archer crit for 38K!",
          "type": "system",
          "time": 1778340501887
        },
        {
          "text": "🪙 Frost Dragon Hatchling killed. +2.4K gold, +3.2K exp.",
          "type": "combat",
          "time": 1778340501886
        },
        {
          "text": "🪙 Frost Dragon killed. +1.8K gold, +2.6K exp.",
          "type": "combat",
          "time": 1778340501885
        },
        {
          "text": "💀 Minotaur Archer crit for 19K!",
          "type": "system",
          "time": 1778340501514
        },
        {
          "text": "🪙 Frost Dragon Hatchling killed. +2.5K gold, +3.7K exp.",
          "type": "combat",
          "time": 1778340501514
        },
        {
          "text": "🪙 Frost Dragon Hatchling killed. +2.7K gold, +2.8K exp.",
          "type": "combat",
          "time": 1778340501513
        },
        {
          "text": "💀 Minotaur Archer crit for 32K!",
          "type": "system",
          "time": 1778340501301
        },
        {
          "text": "🪙 Frost Dragon killed. +1.9K gold, +3.5K exp.",
          "type": "combat",
          "time": 1778340501299
        },
        {
          "text": "🪙 Frost Dragon killed. +2.6K gold, +2.7K exp.",
          "type": "combat",
          "time": 1778340500948
        },
        {
          "text": "🪙 Frost Dragon killed. +1.8K gold, +2.6K exp.",
          "type": "combat",
          "time": 1778340500395
        },
        {
          "text": "💀 Minotaur Archer crit for 40K!",
          "type": "system",
          "time": 1778340500046
        },
        {
          "text": "🪙 Frost Dragon killed. +2.0K gold, +3.6K exp.",
          "type": "combat",
          "time": 1778340500045
        },
        {
          "text": "🪙 Frost Dragon killed. +2.8K gold, +3.6K exp.",
          "type": "combat",
          "time": 1778340499754
        },
        {
          "text": "💀 Minotaur Archer crit for 32K!",
          "type": "system",
          "time": 1778340499446
        },
        {
          "text": "🪙 Frost Dragon killed. +2.6K gold, +3.6K exp.",
          "type": "combat",
          "time": 1778340499445
        },
        {
          "text": "💀 Minotaur Archer crit for 19K!",
          "type": "system",
          "time": 1778340499126
        },
        {
          "text": "👑 Boss dropped: 2 Blue, 3 Yellow, 3 Green",
          "type": "loot",
          "time": 1778340499125
        },
        {
          "text": "👑 [BOSS] Frost Dragon killed. +51K gold, +89K exp.",
          "type": "combat",
          "time": 1778340499124
        },
        {
          "text": "💀 Minotaur Archer crit for 31K!",
          "type": "system",
          "time": 1778340498598
        },
        {
          "text": "🪙 Frost Dragon killed. +2.8K gold, +2.7K exp.",
          "type": "combat",
          "time": 1778340498597
        },
        {
          "text": "💀 Minotaur Archer crit for 25K!",
          "type": "system",
          "time": 1778340498226
        },
        {
          "text": "🪙 Crystal Spider killed. +2.0K gold, +3.0K exp.",
          "type": "combat",
          "time": 1778340498226
        },
        {
          "text": "💀 Minotaur Archer crit for 20K!",
          "type": "system",
          "time": 1778340498218
        },
        {
          "text": "🪙 Frost Dragon killed. +2.3K gold, +3.0K exp.",
          "type": "combat",
          "time": 1778340498217
        },
        {
          "text": "💀 Minotaur Archer crit for 22K!",
          "type": "system",
          "time": 1778340497924
        },
        {
          "text": "💀 Minotaur Archer crit for 27K!",
          "type": "system",
          "time": 1778340497364
        },
        {
          "text": "🪙 Frost Dragon killed. +2.7K gold, +2.5K exp.",
          "type": "combat",
          "time": 1778340497363
        },
        {
          "text": "🪙 Frost Dragon Hatchling killed. +2.7K gold, +2.7K exp.",
          "type": "combat",
          "time": 1778340496798
        },
        {
          "text": "💀 Minotaur Archer crit for 26K!",
          "type": "system",
          "time": 1778340496777
        },
        {
          "text": "🪙 Frost Dragon killed. +2.9K gold, +3.0K exp.",
          "type": "combat",
          "time": 1778340496776
        },
        {
          "text": "🪙 Frost Dragon killed. +2.0K gold, +3.0K exp.",
          "type": "combat",
          "time": 1778340496114
        },
        {
          "text": "💀 Minotaur Archer crit for 24K!",
          "type": "system",
          "time": 1778340495598
        },
        {
          "text": "🪙 Frost Dragon Hatchling killed. +2.0K gold, +3.0K exp.",
          "type": "combat",
          "time": 1778340495597
        }
      ],
      "zoneId": 12,
      "visitedZones": [
        1,
        2,
        3,
        4,
        5,
        6,
        7,
        8,
        9,
        10,
        11,
        12
      ],
      "ownedWeapons": [
        "Sword",
        "Katana",
        "Sabre",
        "Longsword",
        "Scimitar",
        "Broadsword",
        "Bright Sword",
        "Fire Sword",
        "Serpent Sword",
        "Giant Sword",
        "Dragon Slayer",
        "Magic Sword",
        "Mystic Blade",
        "Crystalline Sword"
      ],
      "equippedWeapon": "Crystalline Sword",
      "skillPoints": 137,
      "skills": {
        "sharpshooter": 10,
        "powerBolt": 10,
        "doubleStrike": 10,
        "tripleStrike": 10,
        "headshot": 10,
        "strongerBullets": 10,
        "unlockFireball": 1,
        "fireballCooldown": 10,
        "fireballDamage": 10,
        "unlockLightMagic": 1,
        "lightMagicDamage": 10,
        "lightMagicCooldown": 10,
        "unlockHeavyMagic": 1,
        "heavyMagicDamage": 10,
        "heavyMagicCooldown": 10,
        "deepPockets": 10,
        "experiencedHunter": 10,
        "materialistic": 10,
        "gearingUp": 10,
        "likeABoss": 10,
        "lootHungry": 10,
        "uberDifficulty": 10,
        "darkNovaDamage": 0,
        "darkNovaTargets": 0,
        "decay": 0,
        "deathEcho": 0,
        "overchannel": 0,
        "graveCalling": 0,
        "skeletonReach": 0,
        "skeletonMastery": 0,
        "walkingDead": 0,
        "reanimation": 0,
        "eliteSkeleton": 0,
        "boneArmor": 0,
        "ricochet": 1,
        "openingStrike": 1,
        "burstArrow": 1,
        "followUp": 1,
        "focusedBarrage": 1,
        "bleedingCritical": 1,
        "guillotine": 0
      },
      "materials": {
        "greenEssence": 5857,
        "blueEssence": 1845,
        "yellowEssence": 602,
        "redEssence": 537,
        "whetstones": 15
      },
      "potions": {
        "wealthUntil": 1778337099736,
        "wisdomUntil": 1778337101934,
        "swiftnessUntil": 1778337104077
      },
      "rewards": {
        "showOdds": false,
        "slotCoins": 1,
        "lastCoinAt": 1778340703925,
        "slotSpinning": false,
        "slotOptions": []
      },
      "minDamage": 520,
      "maxDamage": 760,
      "damageUpgradeLevel": 0,
      "maxMonsters": 8,
      "monsters": [],
      "activeSkillTree": "summons",
      "stats": {
        "sessionStartedAt": 1778196703925,
        "goldEarned": 218339668,
        "expEarned": 293742750,
        "monstersKilled": 321832,
        "bossesKilled": 0,
        "ubersKilled": 0,
        "gearFound": 0,
        "starsCollected": 23069,
        "starsEarned": 23069
      },
      "lastSpellCast": {
        "fireball": 1778341011112,
        "lightMagic": 1778341011112,
        "heavyMagic": 1778341011112
      },
      "lastNecromancerAttack": 0,
      "inventory": {
        "treasureChest": 831,
        "chestKey": 0,
        "goldenTreasureChest": 2,
        "skinAscender": 0
      },
      "fishing": {
        "fish": 58,
        "rodOwned": true,
        "lastAttemptAt": 1778341011112,
        "nextAttemptAt": 1778341057612,
        "upgrades": {
          "quickCast": 27,
          "luckyHook": 3,
          "schoolOverflow": 0,
          "doubleHook": 0,
          "tripleHook": 0
        },
        "shopUpgrades": {
          "goldenFish": 0,
          "powerfulFish": 0,
          "empoweredCompanions": 0,
          "biggerPouches": 0,
          "shinierGems": 0,
          "bonusSP": 0
        },
        "golems": {
          "owned": 3,
          "nextAttemptAt": 1778341062112,
          "clockworkCasting": 0,
          "mechanicalPrecision": 0,
          "overclockedEfficiency": 0,
          "precisionHooking": 0,
          "overtunedHooking": 0,
          "placedByZone": {
            "1": 1,
            "2": 1,
            "3": 1
          }
        }
      },
      "skins": {
        "shards": 8,
        "active": {
          "minotaur": "royalHunter"
        },
        "owned": {
          "stargazerArcher": {
            "level": 1,
            "progress": 4,
            "unlocked": true,
            "ascended": false,
            "ascendedLevel": 0,
            "ascendedProgress": 0
          },
          "minotaurFisherman": {
            "level": 20,
            "progress": 0,
            "unlocked": true,
            "ascended": true,
            "ascendedLevel": 20,
            "ascendedProgress": 0
          },
          "royalHunter": {
            "level": 7,
            "progress": 111,
            "unlocked": true,
            "ascended": false,
            "ascendedLevel": 0,
            "ascendedProgress": 0
          }
        }
      },
      "lastSeenAt": 1778341014556,
      "automationToggles": {
        "autoBuy": true,
        "autoTravel": true,
        "autoSkills": true
      },
      "researchBreakthrough": {
        "active": false,
        "closesAt": 0,
        "nextCheckAt": 1778341071921
      },
      "siegeEvent": {
        "active": false,
        "endsAt": 0,
        "nextCheckAt": 1778341071921,
        "nextSpawnAt": 0,
        "wallHp": 731,
        "wallMaxHp": 731,
        "kills": 0,
        "monsters": [],
        "joined": false,
        "rewards": {
          "gold": 0,
          "exp": 0,
          "stars": 0,
          "whetstones": 0,
          "silverTokens": 0,
          "greenEssence": 0,
          "blueEssence": 0,
          "yellowEssence": 0,
          "redEssence": 0,
          "salvageMaterials": 0
        }
      },
      "summonTargetId": "1467c44c-e5e5-478e-9378-8261d03f1ffc",
      "eventReturnZoneId": 12,
      "activeFishingTab": "golems",
      "activeStarforgeTab": "stars",
      "activeSkinsTab": "select",
      "leaderboardSort": "level",
      "starGainSamples": [
        {
          "time": 1778341011108,
          "amount": 1635
        }
      ],
      "loadouts": {
        "activeIndex": 0,
        "stash": [
          {
            "id": "b83b96b8-c384-474a-ad70-c2cde1c9773d",
            "type": "armor",
            "tier": 4,
            "rarity": "rare",
            "rarityName": "Rare",
            "rarityColor": "#4dabf7",
            "name": "Chain Armor",
            "icon": "🥋",
            "sprite": "assets/equipment/armor/chain_armor.gif",
            "stats": {
              "gold": 5,
              "exp": 5,
              "whetstoneChance": 11
            },
            "enhanceLevel": 0
          },
          {
            "id": "67599a62-3dcb-4909-9bef-cb7e1db138db",
            "type": "necklace",
            "tier": 3,
            "rarity": "legendary",
            "rarityName": "Legendary",
            "rarityColor": "#ffb84d",
            "name": "Elven Amulet",
            "icon": "📿",
            "sprite": "assets/equipment/necklace/elven_amulet.gif",
            "stats": {
              "crit": 1,
              "attackSpeed": 17,
              "whetstoneChance": 21,
              "damage": 14
            },
            "enhanceLevel": 0
          },
          {
            "id": "42e28b04-288b-4a10-9f8a-a6db8deaf9ac",
            "type": "ring",
            "tier": 2,
            "rarity": "legendary",
            "rarityName": "Legendary",
            "rarityColor": "#ffb84d",
            "name": "Butterfly Ring",
            "icon": "💍",
            "sprite": "assets/equipment/ring/butterfly_ring.gif",
            "stats": {
              "damage": 9,
              "lootChance": 24,
              "attackSpeed": 12,
              "gold": 4
            },
            "enhanceLevel": 3
          },
          {
            "id": "c5c6928b-2a3d-4e19-9fac-9af7c095686d",
            "type": "helmet",
            "tier": 3,
            "rarity": "rare",
            "rarityName": "Rare",
            "rarityColor": "#4dabf7",
            "name": "Chain Helmet",
            "icon": "⛑",
            "sprite": "assets/equipment/helmet/chain_helmet.gif",
            "stats": {
              "critDamage": 63,
              "gold": 4,
              "crit": 5
            },
            "enhanceLevel": 6
          },
          {
            "id": "e598408b-8021-4104-8531-7eb88f6d98b0",
            "type": "shoes",
            "tier": 3,
            "rarity": "rare",
            "rarityName": "Rare",
            "rarityColor": "#4dabf7",
            "name": "Sandals",
            "icon": "🥾",
            "sprite": "assets/equipment/shoes/sandals.gif",
            "stats": {
              "gold": 13,
              "doubleDrop": 13,
              "exp": 9
            },
            "enhanceLevel": 0
          }
        ],
        "sets": [
          {
            "name": "DAMAGE",
            "slots": {
              "necklace": "67599a62-3dcb-4909-9bef-cb7e1db138db",
              "helmet": "c5c6928b-2a3d-4e19-9fac-9af7c095686d",
              "armor": "b83b96b8-c384-474a-ad70-c2cde1c9773d",
              "shield": null,
              "ring": "42e28b04-288b-4a10-9f8a-a6db8deaf9ac",
              "legs": null,
              "shoes": "e598408b-8021-4104-8531-7eb88f6d98b0"
            }
          },
          {
            "name": "FISHING",
            "slots": {
              "necklace": null,
              "helmet": null,
              "armor": null,
              "shield": null,
              "ring": null,
              "legs": null,
              "shoes": null
            }
          },
          {
            "name": "STARS",
            "slots": {
              "necklace": null,
              "helmet": null,
              "armor": null,
              "shield": null,
              "ring": null,
              "legs": null,
              "shoes": null
            }
          }
        ]
      },
      "offlineSummary": {
        "minutes": 1.50705,
        "gainedLevels": 0,
        "totalGold": 6659,
        "totalExp": 10148,
        "equipmentDrops": 0,
        "whetstones": 0,
        "essenceGains": {
          "greenEssence": 2,
          "blueEssence": 1,
          "yellowEssence": 1,
          "redEssence": 1
        },
        "salvageGains": {
          "commonMaterial": 0,
          "uncommonMaterial": 0,
          "rareMaterial": 0,
          "legendaryMaterial": 0
        }
      }
    },
    "updatedAt": 1778341016903
  },
  "2f0d6431-b0dd-4e08-8ab5-40cde41873cd": {
    "save": {
      "level": 10,
      "exp": 61,
      "gold": 1325,
      "unlockedNodes": [
        "center",
        "minotaur_category",
        "sharpshooter"
      ],
      "monsterResearch": {
        "Rat": {
          "kills": 550,
          "unlocked": []
        },
        "Cave Rat": {
          "kills": 213,
          "unlocked": []
        }
      },
      "weaponStarLevel": 0,
      "dracoWeaponScaling": 0,
      "starsEarned": 0,
      "stars": 0,
      "observatory": {
        "active": false,
        "closesAt": 0,
        "nextCheckAt": 1778343291893
      },
      "starSystem": {
        "activeZoneId": 7,
        "nextZoneSwapAt": 1778344071888,
        "nextSpawnCheckAt": 1778343258888
      },
      "starUpgrades": {
        "starfall": 0,
        "starShower": 0,
        "astralShower": 0,
        "supernovas": 0,
        "supergiants": 0,
        "novaYields": 0,
        "giantYields": 0,
        "cosmicWorth": 0,
        "starHole": 0,
        "stellarYield": 0
      },
      "constellations": {
        "gemini": 0,
        "aries": 0,
        "sagittarius": 0,
        "aquarius": 0,
        "phoenix": 0,
        "draco": 0,
        "taurus": 0,
        "cancer": 0,
        "orion": 0,
        "cetus": 0
      },
      "settings": {
        "minotaurAttacks": true,
        "necromancerAttacks": true,
        "minotaurEffectDebug": false,
        "followStars": false
      },
      "dpsSamples": {
        "minotaur": [],
        "necromancer": []
      },
      "filters": {
        "equipmentAction": "none",
        "rarityLimit": "common"
      },
      "skeletons": [],
      "rebirth": {
        "count": 0,
        "coins": 0
      },
      "rebirthUpgrades": {},
      "equipment": {
        "necklace": null,
        "helmet": null,
        "armor": null,
        "shield": null,
        "ring": null,
        "legs": null,
        "shoes": null
      },
      "equipmentInventory": [],
      "salvageMaterials": {
        "commonMaterial": 0,
        "uncommonMaterial": 0,
        "rareMaterial": 0,
        "legendaryMaterial": 0
      },
      "depot": {
        "activeTab": 0,
        "tabs": [
          [
            {
              "id": "4333faf6-85bc-4be3-a993-42fb3d7dd383",
              "type": "shield",
              "tier": 1,
              "rarity": "common",
              "rarityName": "Common",
              "rarityColor": "#b8b8b8",
              "name": "Wooden Shield",
              "icon": "🛡",
              "sprite": "assets/equipment/shield/wooden_shield.gif",
              "stats": {
                "damage": 1
              },
              "enhanceLevel": 0
            },
            {
              "id": "3e777fa9-931f-4af2-8b4f-61a53bedb53c",
              "type": "helmet",
              "tier": 1,
              "rarity": "uncommon",
              "rarityName": "Uncommon",
              "rarityColor": "#53ff7a",
              "name": "Leather Helmet",
              "icon": "⛑",
              "sprite": "assets/equipment/helmet/leather_helmet.gif",
              "stats": {
                "exp": 2,
                "doubleDrop": 2
              },
              "enhanceLevel": 0
            },
            {
              "id": "b2d22cdf-9338-4dfb-816d-f1dc923d8e0d",
              "type": "legs",
              "tier": 1,
              "rarity": "common",
              "rarityName": "Common",
              "rarityColor": "#b8b8b8",
              "name": "Leather Legs",
              "icon": "👖",
              "sprite": "assets/equipment/legs/leather_legs.gif",
              "stats": {
                "lootChance": 8
              },
              "enhanceLevel": 0
            },
            null,
            null,
            null,
            null,
            null,
            null,
            null,
            null,
            null,
            null,
            null,
            null,
            null,
            null,
            null,
            null,
            null,
            null,
            null,
            null,
            null,
            null,
            null,
            null,
            null,
            null,
            null,
            null,
            null,
            null,
            null,
            null,
            null,
            null,
            null,
            null,
            null
          ],
          [
            null,
            null,
            null,
            null,
            null,
            null,
            null,
            null,
            null,
            null,
            null,
            null,
            null,
            null,
            null,
            null,
            null,
            null,
            null,
            null,
            null,
            null,
            null,
            null,
            null,
            null,
            null,
            null,
            null,
            null,
            null,
            null,
            null,
            null,
            null,
            null,
            null,
            null,
            null,
            null
          ],
          [
            null,
            null,
            null,
            null,
            null,
            null,
            null,
            null,
            null,
            null,
            null,
            null,
            null,
            null,
            null,
            null,
            null,
            null,
            null,
            null,
            null,
            null,
            null,
            null,
            null,
            null,
            null,
            null,
            null,
            null,
            null,
            null,
            null,
            null,
            null,
            null,
            null,
            null,
            null,
            null
          ]
        ]
      },
      "activeLogFilter": "all",
      "logMessages": [
        {
          "text": "🪙 Rat killed. +2 gold, +6 exp.",
          "type": "combat",
          "time": 1778343208881
        },
        {
          "text": "✨ Stars are now falling in Meriana Gargoyle Cave!",
          "type": "system",
          "time": 1778343171889
        },
        {
          "text": "🪙 Rat killed. +5 gold, +6 exp.",
          "type": "combat",
          "time": 1778342902771
        },
        {
          "text": "🪙 Rat killed. +4 gold, +6 exp.",
          "type": "combat",
          "time": 1778342899260
        },
        {
          "text": "🪙 Rat killed. +2 gold, +5 exp.",
          "type": "combat",
          "time": 1778342894693
        },
        {
          "text": "🪙 Rat killed. +4 gold, +8 exp.",
          "type": "combat",
          "time": 1778342890223
        },
        {
          "text": "🪙 Cave Rat killed. +4 gold, +4 exp.",
          "type": "combat",
          "time": 1778342885674
        },
        {
          "text": "🧩 Common Leather Legs dropped!",
          "type": "loot",
          "time": 1778342882140
        },
        {
          "text": "🪙 Cave Rat killed. +3 gold, +8 exp.",
          "type": "combat",
          "time": 1778342882139
        },
        {
          "text": "🪙 Cave Rat killed. +3 gold, +6 exp.",
          "type": "combat",
          "time": 1778342877610
        },
        {
          "text": "🪙 Cave Rat killed. +5 gold, +8 exp.",
          "type": "combat",
          "time": 1778342873086
        },
        {
          "text": "🪙 Rat killed. +5 gold, +7 exp.",
          "type": "combat",
          "time": 1778342869530
        },
        {
          "text": "🪙 Rat killed. +3 gold, +6 exp.",
          "type": "combat",
          "time": 1778342865007
        },
        {
          "text": "🪙 Rat killed. +4 gold, +7 exp.",
          "type": "combat",
          "time": 1778342861464
        },
        {
          "text": "🪙 Rat killed. +4 gold, +5 exp.",
          "type": "combat",
          "time": 1778342857798
        },
        {
          "text": "🪙 Rat killed. +2 gold, +8 exp.",
          "type": "combat",
          "time": 1778342853333
        },
        {
          "text": "🪙 Rat killed. +4 gold, +6 exp.",
          "type": "combat",
          "time": 1778342849767
        },
        {
          "text": "🪙 Cave Rat killed. +3 gold, +7 exp.",
          "type": "combat",
          "time": 1778342846168
        },
        {
          "text": "🪙 Cave Rat killed. +3 gold, +5 exp.",
          "type": "combat",
          "time": 1778342842524
        },
        {
          "text": "🪙 Rat killed. +5 gold, +4 exp.",
          "type": "combat",
          "time": 1778342838963
        },
        {
          "text": "🪙 Rat killed. +2 gold, +7 exp.",
          "type": "combat",
          "time": 1778342834463
        },
        {
          "text": "🪙 Rat killed. +2 gold, +7 exp.",
          "type": "combat",
          "time": 1778342829024
        },
        {
          "text": "🪙 Rat killed. +3 gold, +4 exp.",
          "type": "combat",
          "time": 1778342825443
        },
        {
          "text": "🪙 Rat killed. +4 gold, +8 exp.",
          "type": "combat",
          "time": 1778342820919
        },
        {
          "text": "🪙 Cave Rat killed. +4 gold, +4 exp.",
          "type": "combat",
          "time": 1778342816423
        },
        {
          "text": "🪙 Rat killed. +5 gold, +6 exp.",
          "type": "combat",
          "time": 1778342812836
        },
        {
          "text": "🪙 Cave Rat killed. +2 gold, +6 exp.",
          "type": "combat",
          "time": 1778342809231
        },
        {
          "text": "🪙 Rat killed. +4 gold, +7 exp.",
          "type": "combat",
          "time": 1778342792012
        },
        {
          "text": "🪙 Rat killed. +5 gold, +7 exp.",
          "type": "combat",
          "time": 1778342752272
        },
        {
          "text": "🪙 Cave Rat killed. +5 gold, +5 exp.",
          "type": "combat",
          "time": 1778342747731
        },
        {
          "text": "🪙 Rat killed. +3 gold, +5 exp.",
          "type": "combat",
          "time": 1778342744152
        },
        {
          "text": "🪙 Rat killed. +3 gold, +7 exp.",
          "type": "combat",
          "time": 1778342739714
        },
        {
          "text": "🪙 Cave Rat killed. +5 gold, +4 exp.",
          "type": "combat",
          "time": 1778342736131
        },
        {
          "text": "🪙 Rat killed. +5 gold, +6 exp.",
          "type": "combat",
          "time": 1778342731578
        },
        {
          "text": "🪙 Cave Rat killed. +5 gold, +8 exp.",
          "type": "combat",
          "time": 1778342727080
        },
        {
          "text": "🪙 Rat killed. +3 gold, +4 exp.",
          "type": "combat",
          "time": 1778342722563
        },
        {
          "text": "🪙 Rat killed. +4 gold, +8 exp.",
          "type": "combat",
          "time": 1778342718081
        },
        {
          "text": "🪙 Rat killed. +4 gold, +8 exp.",
          "type": "combat",
          "time": 1778342713543
        },
        {
          "text": "🪙 Rat killed. +3 gold, +7 exp.",
          "type": "combat",
          "time": 1778342710002
        },
        {
          "text": "🪙 Rat killed. +5 gold, +8 exp.",
          "type": "combat",
          "time": 1778342706397
        },
        {
          "text": "🪙 Rat killed. +3 gold, +8 exp.",
          "type": "combat",
          "time": 1778342702736
        },
        {
          "text": "🪙 Rat killed. +5 gold, +7 exp.",
          "type": "combat",
          "time": 1778342698273
        },
        {
          "text": "🪙 Rat killed. +4 gold, +4 exp.",
          "type": "combat",
          "time": 1778342693760
        },
        {
          "text": "👑 Boss dropped: 1 Yellow, 3 Green",
          "type": "loot",
          "time": 1778342690202
        },
        {
          "text": "👑 [BOSS] Rat killed. +75 gold, +200 exp.",
          "type": "combat",
          "time": 1778342690201
        },
        {
          "text": "🪙 Rat killed. +2 gold, +5 exp.",
          "type": "combat",
          "time": 1778342669962
        },
        {
          "text": "🪙 Cave Rat killed. +4 gold, +6 exp.",
          "type": "combat",
          "time": 1778342665783
        },
        {
          "text": "🪙 Rat killed. +2 gold, +6 exp.",
          "type": "combat",
          "time": 1778342662195
        },
        {
          "text": "🪙 Rat killed. +2 gold, +6 exp.",
          "type": "combat",
          "time": 1778342658597
        },
        {
          "text": "🪙 Rat killed. +3 gold, +5 exp.",
          "type": "combat",
          "time": 1778342655006
        },
        {
          "text": "🪙 Rat killed. +5 gold, +5 exp.",
          "type": "combat",
          "time": 1778342651354
        },
        {
          "text": "🪙 Rat killed. +3 gold, +4 exp.",
          "type": "combat",
          "time": 1778342647736
        },
        {
          "text": "🪙 Rat killed. +3 gold, +4 exp.",
          "type": "combat",
          "time": 1778342644119
        },
        {
          "text": "🪙 Rat killed. +3 gold, +8 exp.",
          "type": "combat",
          "time": 1778342640525
        },
        {
          "text": "🪙 Rat killed. +5 gold, +5 exp.",
          "type": "combat",
          "time": 1778342636064
        },
        {
          "text": "🪙 Cave Rat killed. +3 gold, +4 exp.",
          "type": "combat",
          "time": 1778342632455
        },
        {
          "text": "🪙 Rat killed. +4 gold, +4 exp.",
          "type": "combat",
          "time": 1778342627994
        },
        {
          "text": "🪙 Rat killed. +3 gold, +8 exp.",
          "type": "combat",
          "time": 1778342623482
        },
        {
          "text": "🪙 Rat killed. +3 gold, +5 exp.",
          "type": "combat",
          "time": 1778342618934
        },
        {
          "text": "🪙 Cave Rat killed. +4 gold, +4 exp.",
          "type": "combat",
          "time": 1778342615350
        },
        {
          "text": "🪙 Rat killed. +5 gold, +6 exp.",
          "type": "combat",
          "time": 1778342611757
        },
        {
          "text": "🪙 Rat killed. +5 gold, +4 exp.",
          "type": "combat",
          "time": 1778342608142
        },
        {
          "text": "🪙 Rat killed. +5 gold, +5 exp.",
          "type": "combat",
          "time": 1778342604552
        },
        {
          "text": "🪙 Rat killed. +3 gold, +7 exp.",
          "type": "combat",
          "time": 1778342600016
        },
        {
          "text": "🪙 Rat killed. +4 gold, +7 exp.",
          "type": "combat",
          "time": 1778342596474
        },
        {
          "text": "🪙 Cave Rat killed. +3 gold, +5 exp.",
          "type": "combat",
          "time": 1778342592864
        },
        {
          "text": "🪙 Cave Rat killed. +4 gold, +6 exp.",
          "type": "combat",
          "time": 1778342588380
        },
        {
          "text": "🪙 Rat killed. +4 gold, +4 exp.",
          "type": "combat",
          "time": 1778342584812
        },
        {
          "text": "🪙 Rat killed. +2 gold, +4 exp.",
          "type": "combat",
          "time": 1778342581151
        },
        {
          "text": "🪙 Rat killed. +4 gold, +8 exp.",
          "type": "combat",
          "time": 1778342577521
        },
        {
          "text": "🪙 Rat killed. +4 gold, +7 exp.",
          "type": "combat",
          "time": 1778342574008
        },
        {
          "text": "🪙 Rat killed. +3 gold, +5 exp.",
          "type": "combat",
          "time": 1778342569517
        },
        {
          "text": "🪙 Cave Rat killed. +3 gold, +4 exp.",
          "type": "combat",
          "time": 1778342565867
        },
        {
          "text": "🪙 Rat killed. +2 gold, +6 exp.",
          "type": "combat",
          "time": 1778342562295
        },
        {
          "text": "🪙 Rat killed. +3 gold, +8 exp.",
          "type": "combat",
          "time": 1778342559535
        },
        {
          "text": "🪙 Rat killed. +4 gold, +8 exp.",
          "type": "combat",
          "time": 1778342555917
        },
        {
          "text": "🪙 Rat killed. +2 gold, +4 exp.",
          "type": "combat",
          "time": 1778342552333
        },
        {
          "text": "🪙 Cave Rat killed. +5 gold, +8 exp.",
          "type": "combat",
          "time": 1778342547877
        },
        {
          "text": "🪙 Rat killed. +5 gold, +8 exp.",
          "type": "combat",
          "time": 1778342544288
        },
        {
          "text": "🪙 Rat killed. +3 gold, +8 exp.",
          "type": "combat",
          "time": 1778342540647
        },
        {
          "text": "🪙 Rat killed. +4 gold, +7 exp.",
          "type": "combat",
          "time": 1778342537039
        },
        {
          "text": "🪙 Rat killed. +3 gold, +6 exp.",
          "type": "combat",
          "time": 1778342534318
        },
        {
          "text": "🪙 Rat killed. +2 gold, +7 exp.",
          "type": "combat",
          "time": 1778342530730
        },
        {
          "text": "🪙 Cave Rat killed. +3 gold, +8 exp.",
          "type": "combat",
          "time": 1778342527137
        },
        {
          "text": "🪙 Rat killed. +4 gold, +4 exp.",
          "type": "combat",
          "time": 1778342522659
        },
        {
          "text": "🧪 Green Essence dropped.",
          "type": "loot",
          "time": 1778342519025
        },
        {
          "text": "🪙 Rat killed. +5 gold, +4 exp.",
          "type": "combat",
          "time": 1778342519025
        },
        {
          "text": "🪙 Rat killed. +2 gold, +6 exp.",
          "type": "combat",
          "time": 1778342514573
        },
        {
          "text": "🪙 Rat killed. +3 gold, +6 exp.",
          "type": "combat",
          "time": 1778342510945
        },
        {
          "text": "🪙 Rat killed. +4 gold, +4 exp.",
          "type": "combat",
          "time": 1778342507394
        },
        {
          "text": "🪙 Cave Rat killed. +5 gold, +7 exp.",
          "type": "combat",
          "time": 1778342502841
        },
        {
          "text": "🪙 Rat killed. +3 gold, +7 exp.",
          "type": "combat",
          "time": 1778342499278
        },
        {
          "text": "🪙 Rat killed. +4 gold, +5 exp.",
          "type": "combat",
          "time": 1778342495708
        },
        {
          "text": "🪙 Cave Rat killed. +2 gold, +8 exp.",
          "type": "combat",
          "time": 1778342492038
        },
        {
          "text": "🪙 Rat killed. +3 gold, +4 exp.",
          "type": "combat",
          "time": 1778342487617
        },
        {
          "text": "🪙 Rat killed. +5 gold, +7 exp.",
          "type": "combat",
          "time": 1778342483943
        },
        {
          "text": "🪙 Cave Rat killed. +3 gold, +8 exp.",
          "type": "combat",
          "time": 1778342480360
        },
        {
          "text": "🪙 Rat killed. +2 gold, +5 exp.",
          "type": "combat",
          "time": 1778342476743
        },
        {
          "text": "🪙 Rat killed. +4 gold, +5 exp.",
          "type": "combat",
          "time": 1778342472222
        },
        {
          "text": "🪙 Rat killed. +4 gold, +5 exp.",
          "type": "combat",
          "time": 1778342468676
        },
        {
          "text": "🪙 Cave Rat killed. +2 gold, +7 exp.",
          "type": "combat",
          "time": 1778342464199
        },
        {
          "text": "🪙 Rat killed. +5 gold, +7 exp.",
          "type": "combat",
          "time": 1778342459701
        },
        {
          "text": "🪙 Rat killed. +3 gold, +5 exp.",
          "type": "combat",
          "time": 1778342455195
        },
        {
          "text": "🪙 Cave Rat killed. +4 gold, +7 exp.",
          "type": "combat",
          "time": 1778342450640
        },
        {
          "text": "🪙 Rat killed. +5 gold, +7 exp.",
          "type": "combat",
          "time": 1778342446173
        },
        {
          "text": "🪙 Cave Rat killed. +2 gold, +5 exp.",
          "type": "combat",
          "time": 1778342442579
        },
        {
          "text": "🪙 Rat killed. +4 gold, +7 exp.",
          "type": "combat",
          "time": 1778342438913
        },
        {
          "text": "🪙 Rat killed. +4 gold, +7 exp.",
          "type": "combat",
          "time": 1778342435354
        },
        {
          "text": "🪙 Rat killed. +4 gold, +8 exp.",
          "type": "combat",
          "time": 1778342431779
        },
        {
          "text": "🪙 Rat killed. +4 gold, +4 exp.",
          "type": "combat",
          "time": 1778342428142
        },
        {
          "text": "🪙 Rat killed. +4 gold, +7 exp.",
          "type": "combat",
          "time": 1778342424555
        },
        {
          "text": "🪙 Rat killed. +4 gold, +8 exp.",
          "type": "combat",
          "time": 1778342420099
        },
        {
          "text": "🪙 Cave Rat killed. +5 gold, +5 exp.",
          "type": "combat",
          "time": 1778342416421
        },
        {
          "text": "🪙 Rat killed. +5 gold, +8 exp.",
          "type": "combat",
          "time": 1778342412869
        },
        {
          "text": "🪙 Cave Rat killed. +2 gold, +5 exp.",
          "type": "combat",
          "time": 1778342407426
        },
        {
          "text": "🪙 Rat killed. +2 gold, +5 exp.",
          "type": "combat",
          "time": 1778342402945
        },
        {
          "text": "🪙 Rat killed. +2 gold, +6 exp.",
          "type": "combat",
          "time": 1778342398489
        },
        {
          "text": "🪙 Rat killed. +3 gold, +6 exp.",
          "type": "combat",
          "time": 1778342394888
        },
        {
          "text": "🪙 Rat killed. +3 gold, +4 exp.",
          "type": "combat",
          "time": 1778342390354
        },
        {
          "text": "🪙 Cave Rat killed. +2 gold, +8 exp.",
          "type": "combat",
          "time": 1778342385886
        }
      ],
      "zoneId": 1,
      "visitedZones": [
        1
      ],
      "ownedWeapons": [
        "Sword"
      ],
      "equippedWeapon": "Sword",
      "skillPoints": 7,
      "skills": {
        "sharpshooter": 2,
        "powerBolt": 0,
        "doubleStrike": 0,
        "tripleStrike": 0,
        "headshot": 0,
        "strongerBullets": 0,
        "unlockFireball": 0,
        "fireballCooldown": 0,
        "fireballDamage": 0,
        "unlockLightMagic": 0,
        "lightMagicDamage": 0,
        "lightMagicCooldown": 0,
        "unlockHeavyMagic": 0,
        "heavyMagicDamage": 0,
        "heavyMagicCooldown": 0,
        "deepPockets": 0,
        "experiencedHunter": 0,
        "materialistic": 0,
        "gearingUp": 0,
        "likeABoss": 0,
        "lootHungry": 0,
        "uberDifficulty": 0,
        "darkNovaDamage": 0,
        "darkNovaTargets": 0,
        "decay": 0,
        "deathEcho": 0,
        "overchannel": 0,
        "graveCalling": 0,
        "skeletonReach": 0,
        "skeletonMastery": 0,
        "walkingDead": 0,
        "reanimation": 0,
        "eliteSkeleton": 0,
        "boneArmor": 0
      },
      "materials": {
        "greenEssence": 15,
        "blueEssence": 3,
        "yellowEssence": 3,
        "redEssence": 1,
        "whetstones": 1
      },
      "potions": {
        "wealthUntil": 0,
        "wisdomUntil": 0,
        "swiftnessUntil": 0
      },
      "rewards": {
        "showOdds": false,
        "slotCoins": 0,
        "lastCoinAt": 1778341319734,
        "slotSpinning": false,
        "slotOptions": []
      },
      "minDamage": 5,
      "maxDamage": 10,
      "damageUpgradeLevel": 0,
      "maxMonsters": 8,
      "monsters": [],
      "activeSkillTree": "summons",
      "stats": {
        "sessionStartedAt": 1778341319734,
        "goldEarned": 1325,
        "expEarned": 2267,
        "monstersKilled": 303,
        "bossesKilled": 0,
        "ubersKilled": 0,
        "gearFound": 0
      },
      "lastSpellCast": {
        "fireball": 0,
        "lightMagic": 0,
        "heavyMagic": 0
      },
      "lastNecromancerAttack": 0,
      "inventory": {
        "treasureChest": 1,
        "chestKey": 0,
        "goldenTreasureChest": 0,
        "skinAscender": 0
      },
      "fishing": {
        "fish": 2,
        "rodOwned": true,
        "lastAttemptAt": 1778343231893,
        "nextAttemptAt": 1778343291893,
        "upgrades": {
          "quickCast": 0,
          "luckyHook": 0,
          "schoolOverflow": 0,
          "doubleHook": 0,
          "tripleHook": 0
        },
        "shopUpgrades": {
          "goldenFish": 0,
          "powerfulFish": 0,
          "empoweredCompanions": 0,
          "biggerPouches": 0,
          "shinierGems": 0,
          "bonusSP": 0
        },
        "golems": {
          "owned": 0,
          "nextAttemptAt": 1778341379736,
          "clockworkCasting": 0,
          "mechanicalPrecision": 0,
          "overclockedEfficiency": 0,
          "precisionHooking": 0,
          "overtunedHooking": 0,
          "placedByZone": {}
        }
      },
      "skins": {
        "shards": 0,
        "active": {
          "minotaur": "stargazerArcher"
        },
        "owned": {
          "stargazerArcher": {
            "level": 0,
            "progress": 0,
            "ascended": false,
            "ascendedLevel": 0,
            "ascendedProgress": 0,
            "unlocked": true
          },
          "minotaurFisherman": {
            "level": 0,
            "progress": 0,
            "ascended": false,
            "ascendedLevel": 0,
            "ascendedProgress": 0,
            "unlocked": false
          },
          "royalHunter": {
            "level": 0,
            "progress": 0,
            "ascended": false,
            "ascendedLevel": 0,
            "ascendedProgress": 0,
            "unlocked": false
          }
        }
      },
      "lastSeenAt": 1778343255888,
      "automationToggles": {
        "autoBuy": true,
        "autoTravel": true,
        "autoSkills": true
      },
      "researchBreakthrough": {
        "active": false,
        "closesAt": 0,
        "nextCheckAt": 1778343291893
      },
      "siegeEvent": {
        "active": false,
        "endsAt": 0,
        "nextCheckAt": 1778343291893,
        "nextSpawnAt": 0,
        "wallHp": 0,
        "wallMaxHp": 0,
        "kills": 0,
        "monsters": []
      },
      "summonTargetId": "501b16ee-03a9-4b49-8ca6-5ec1981decad",
      "leaderboardSort": "level",
      "activeFishingTab": "rod",
      "loadouts": {
        "activeIndex": 0,
        "stash": [],
        "sets": [
          {
            "name": "Loadout 1",
            "slots": {
              "necklace": null,
              "helmet": null,
              "armor": null,
              "shield": null,
              "ring": null,
              "legs": null,
              "shoes": null
            }
          },
          {
            "name": "Loadout 2",
            "slots": {
              "necklace": null,
              "helmet": null,
              "armor": null,
              "shield": null,
              "ring": null,
              "legs": null,
              "shoes": null
            }
          },
          {
            "name": "Loadout 3",
            "slots": {
              "necklace": null,
              "helmet": null,
              "armor": null,
              "shield": null,
              "ring": null,
              "legs": null,
              "shoes": null
            }
          }
        ]
      }
    },
    "updatedAt": 1778343257902
  }
}